pre_commit_hooks/__init__.py
pre_commit_hooks/check_added_large_files.py
pre_commit_hooks/check_ast.py
pre_commit_hooks/check_builtin_literals.py
pre_commit_hooks/check_byte_order_marker.py
pre_commit_hooks/check_case_conflict.py
pre_commit_hooks/check_docstring_first.py
pre_commit_hooks/check_executables_have_shebangs.py
pre_commit_hooks/check_json.py
pre_commit_hooks/check_merge_conflict.py
pre_commit_hooks/check_shebang_scripts_are_executable.py
pre_commit_hooks/check_symlinks.py
pre_commit_hooks/check_toml.py
pre_commit_hooks/check_vcs_permalinks.py
pre_commit_hooks/check_xml.py
pre_commit_hooks/check_yaml.py
pre_commit_hooks/debug_statement_hook.py
pre_commit_hooks/destroyed_symlinks.py
pre_commit_hooks/detect_aws_credentials.py
pre_commit_hooks/detect_private_key.py
pre_commit_hooks/end_of_file_fixer.py
pre_commit_hooks/file_contents_sorter.py
pre_commit_hooks/fix_byte_order_marker.py
pre_commit_hooks/fix_encoding_pragma.py
pre_commit_hooks/forbid_new_submodules.py
pre_commit_hooks/mixed_line_ending.py
pre_commit_hooks/no_commit_to_branch.py
pre_commit_hooks/pretty_format_json.py
pre_commit_hooks/removed.py
pre_commit_hooks/requirements_txt_fixer.py
pre_commit_hooks/sort_simple_yaml.py
pre_commit_hooks/string_fixer.py
pre_commit_hooks/tests_should_end_in_test.py
pre_commit_hooks/trailing_whitespace_fixer.py
pre_commit_hooks/util.py
pre_commit_hooks-4.6.0.dist-info/LICENSE
pre_commit_hooks-4.6.0.dist-info/METADATA
pre_commit_hooks-4.6.0.dist-info/WHEEL
pre_commit_hooks-4.6.0.dist-info/entry_points.txt
pre_commit_hooks-4.6.0.dist-info/top_level.txt
pre_commit_hooks-4.6.0.dist-info/RECORD
