Metadata-Version: 2.1
Name: pre-commit-hooks
Version: 4.6.0
Summary: Some out-of-the-box hooks for pre-commit.
Home-page: https://github.com/pre-commit/pre-commit-hooks
Author: Anthony Sottile
Author-email: asottile@umich.edu
License: MIT
Classifier: License :: OSI Approved :: MIT License
Classifier: Programming Language :: Python :: 3
Classifier: Programming Language :: Python :: 3 :: Only
Classifier: Programming Language :: Python :: Implementation :: CPython
Classifier: Programming Language :: Python :: Implementation :: PyPy
Requires-Python: >=3.8
License-File: LICENSE
Requires-Dist: ruamel.yaml (>=0.15)
Requires-Dist: tomli (>=1.1.0) ; python_version < "3.11"
